circular_buffer_numpy/__init__.py
circular_buffer_numpy/_version.py
circular_buffer_numpy/circular_buffer.py
circular_buffer_numpy/queue.py
circular_buffer_numpy/tests/__init__.py
circular_buffer_numpy/tests/conftest.py
circular_buffer_numpy/tests/test_circular_buffer.py
circular_buffer_numpy/tests/test_queue.py
circular_buffer_numpy-0.2.4.dist-info/AUTHORS.rst
circular_buffer_numpy-0.2.4.dist-info/LICENSE
circular_buffer_numpy-0.2.4.dist-info/METADATA
circular_buffer_numpy-0.2.4.dist-info/WHEEL
circular_buffer_numpy-0.2.4.dist-info/top_level.txt
circular_buffer_numpy-0.2.4.dist-info/RECORD
