Metadata-Version: 2.1
Name: circular-buffer-numpy
Version: 0.2.4
Summary: Package for circular buffer numpy array
Home-page: https://github.com/vstadnytskyi/circular_buffer_numpy
Author: Valentyn Stadnytskyi
Author-email: v.stadnytskyi@gmail.com
License: BSD (3-clause)
Classifier: Development Status :: 2 - Pre-Alpha
Classifier: Natural Language :: English
Classifier: Programming Language :: Python :: 3
Requires-Python: >=3.6
License-File: LICENSE
License-File: AUTHORS.rst
Requires-Dist: numpy
Requires-Dist: ubcs-auxiliary
